taptempo/__init__.py
taptempo/__main__.py
taptempo/gui.py
taptempo/midi.py
taptempo/taptempo.py
taptempo-1.1.1.data/scripts/taptempo
taptempo-1.1.1.dist-info/LICENSE
taptempo-1.1.1.dist-info/METADATA
taptempo-1.1.1.dist-info/WHEEL
taptempo-1.1.1.dist-info/top_level.txt
taptempo-1.1.1.dist-info/RECORD
